{
  "/_global-error/page": "app/_global-error/page.js",
  "/_not-found/page": "app/_not-found/page.js",
  "/api/auth/login/route": "app/api/auth/login/route.js",
  "/api/auth/logout/route": "app/api/auth/logout/route.js",
  "/api/auth/me/route": "app/api/auth/me/route.js",
  "/api/auth/register/route": "app/api/auth/register/route.js",
  "/api/meals/route": "app/api/meals/route.js",
  "/api/posts/[id]/comments/route": "app/api/posts/[id]/comments/route.js",
  "/api/posts/[id]/like/route": "app/api/posts/[id]/like/route.js",
  "/api/posts/route": "app/api/posts/route.js",
  "/api/user/profile/route": "app/api/user/profile/route.js",
  "/api/weight/route": "app/api/weight/route.js",
  "/auth/login/page": "app/auth/login/page.js",
  "/auth/register/page": "app/auth/register/page.js",
  "/calculator/page": "app/calculator/page.js",
  "/community/page": "app/community/page.js",
  "/dashboard/page": "app/dashboard/page.js",
  "/diet/page": "app/diet/page.js",
  "/favicon.ico/route": "app/favicon.ico/route.js",
  "/page": "app/page.js",
  "/profile/page": "app/profile/page.js",
  "/weight/page": "app/weight/page.js"
}